{
	"meta": {
		"template": "default.html"
	},
	"head": {},
	"body": {
		"free": [
			{
				"type": "layout.div",
				"attr": {},
				"data": [
					{
						"type": "tag.p",
						"data": ".default",
						"attr": {
							"css": "_cms_test_h2",
							"class": "_cms_test_h2"
						}
					},
					{
						"type": "tag.heading",
						"data": {
							"heading": "h1",
							"main": {
								"text": "<em>h1</em> タイトル",
								"link": null
							},
							"right": {
								"text": " タイトル",
								"link": null
							}
						},
						"attr": {
							"css": "default",
							"narrow": "",
							"class": "default",
							"hide": ""
						}
					},
					{
						"type": "tag.heading",
						"data": {
							"heading": "h2",
							"main": {
								"text": "<em>h2</em> タイトル",
								"link": null
							},
							"right": {
								"text": " タイトル",
								"link": null
							}
						},
						"attr": {
							"css": "default",
							"narrow": "",
							"class": "default",
							"hide": ""
						}
					},
					{
						"type": "tag.heading",
						"data": {
							"heading": "h3",
							"main": {
								"text": "<em>h3</em> タイトル",
								"link": null
							},
							"right": {
								"text": " タイトル",
								"link": null
							}
						},
						"attr": {
							"css": "default",
							"narrow": "",
							"class": "default",
							"hide": ""
						}
					},
					{
						"type": "tag.heading",
						"data": {
							"heading": "h3",
							"main": {
								"text": "<em>h3</em> タイトル",
								"link": null
							},
							"right": {
								"text": " タイトル",
								"link": null
							}
						},
						"attr": {
							"css": "default",
							"narrow": "",
							"class": "default",
							"hide": ""
						}
					},
					{
						"type": "tag.p",
						"data": ".waku",
						"attr": {
							"css": "_cms_test_h2",
							"class": "_cms_test_h2"
						}
					},
					{
						"type": "tag.heading",
						"data": {
							"heading": "h1",
							"main": {
								"text": "<em>h1</em> タイトル",
								"link": null
							},
							"right": {
								"text": " タイトル",
								"link": null
							}
						},
						"attr": {
							"css": "default line",
							"narrow": "",
							"class": "default line",
							"hide": ""
						}
					},
					{
						"type": "tag.heading",
						"data": {
							"heading": "h2",
							"main": {
								"text": "<em>h2</em> タイトル",
								"link": null
							},
							"right": {
								"text": " タイトル",
								"link": null
							}
						},
						"attr": {
							"css": "default line",
							"narrow": "",
							"class": "default line",
							"hide": ""
						}
					},
					{
						"type": "tag.heading",
						"data": {
							"heading": "h3",
							"main": {
								"text": "<em>h3</em> タイトル",
								"link": null
							},
							"right": {
								"text": " タイトル",
								"link": null
							}
						},
						"attr": {
							"css": "default line",
							"narrow": "",
							"class": "default line",
							"hide": ""
						}
					},
					{
						"type": "tag.heading",
						"data": {
							"heading": "h4",
							"main": {
								"text": "<em>h4</em> タイトル",
								"link": null
							},
							"right": {
								"text": " タイトル",
								"link": null
							}
						},
						"attr": {
							"css": "default line",
							"narrow": "",
							"class": "default line",
							"hide": ""
						}
					},
					{
						"type": "tag.p",
						"data": "h1.line",
						"attr": {
							"css": "_cms_test_h2",
							"class": "_cms_test_h2"
						}
					},
					{
						"type": "tag.heading",
						"data": {
							"heading": "h1",
							"main": {
								"text": "<em>h1</em> タイトル",
								"link": null
							},
							"right": {
								"text": " タイトル",
								"link": null
							}
						},
						"attr": {
							"css": "default line-b",
							"narrow": "",
							"class": "default line-b",
							"hide": ""
						}
					},
					{
						"type": "tag.heading",
						"data": {
							"heading": "h2",
							"main": {
								"text": "<em>h2</em> タイトル",
								"link": null
							},
							"right": {
								"text": " タイトル",
								"link": null
							}
						},
						"attr": {
							"css": "default line-b",
							"narrow": "",
							"class": "default line-b",
							"hide": ""
						}
					},
					{
						"type": "tag.heading",
						"data": {
							"heading": "h2",
							"main": {
								"text": "<em>h3</em> タイトル",
								"link": null
							},
							"right": {
								"text": " タイトル",
								"link": null
							}
						},
						"attr": {
							"css": "default line-b",
							"narrow": "",
							"class": "default line-b",
							"hide": ""
						}
					},
					{
						"type": "tag.heading",
						"data": {
							"heading": "h4",
							"main": {
								"text": "<em>h4</em> タイトル",
								"link": null
							},
							"right": {
								"text": " タイトル",
								"link": null
							}
						},
						"attr": {
							"css": "default line-b",
							"narrow": "",
							"class": "default line-b",
							"hide": ""
						}
					},
					{
						"type": "tag.p",
						"data": ".glay",
						"attr": {
							"css": "_cms_test_h2",
							"class": "_cms_test_h2"
						}
					},
					{
						"type": "tag.heading",
						"data": {
							"heading": "h1",
							"main": {
								"text": "<em>h2</em> タイトル",
								"link": null
							},
							"right": {
								"text": " タイトル",
								"link": null
							}
						},
						"attr": {
							"css": "default glay",
							"narrow": "",
							"class": "default glay",
							"hide": ""
						}
					},
					{
						"type": "tag.heading",
						"data": {
							"heading": "h2",
							"main": {
								"text": "<em>h2</em> タイトル",
								"link": null
							},
							"right": {
								"text": " タイトル",
								"link": null
							}
						},
						"attr": {
							"css": " glay default",
							"narrow": "",
							"class": " glay default",
							"hide": ""
						}
					},
					{
						"type": "tag.heading",
						"data": {
							"heading": "h3",
							"main": {
								"text": "<em>h3</em> タイトル",
								"link": null
							},
							"right": {
								"text": " タイトル",
								"link": null
							}
						},
						"attr": {
							"css": "default glay",
							"narrow": "",
							"class": "default glay",
							"hide": ""
						}
					},
					{
						"type": "tag.heading",
						"data": {
							"heading": "h4",
							"main": {
								"text": "<em>h4</em> タイトル",
								"link": null
							},
							"right": {
								"text": " タイトル",
								"link": null
							}
						},
						"attr": {
							"css": "default glay",
							"narrow": "",
							"class": "default glay",
							"hide": ""
						}
					},
					{
						"type": "tag.p",
						"data": ".black",
						"attr": {
							"css": "_cms_test_h2",
							"class": "_cms_test_h2"
						}
					},
					{
						"type": "tag.heading",
						"data": {
							"heading": "h1",
							"main": {
								"text": "<em>h2</em> タイトル",
								"link": null
							},
							"right": {
								"text": " タイトル",
								"link": null
							}
						},
						"attr": {
							"css": "default black",
							"narrow": "",
							"class": "default black",
							"hide": ""
						}
					},
					{
						"type": "tag.heading",
						"data": {
							"heading": "h2",
							"main": {
								"text": "<em>h2</em> タイトル",
								"link": null
							},
							"right": {
								"text": " タイトル",
								"link": null
							}
						},
						"attr": {
							"css": "default black",
							"narrow": "",
							"class": "default black",
							"hide": ""
						}
					},
					{
						"type": "tag.heading",
						"data": {
							"heading": "h3",
							"main": {
								"text": "<em>h3</em> タイトル",
								"link": null
							},
							"right": {
								"text": " タイトル",
								"link": null
							}
						},
						"attr": {
							"css": "default black",
							"narrow": "",
							"class": "default black",
							"hide": ""
						}
					},
					{
						"type": "tag.heading",
						"data": {
							"heading": "h4",
							"main": {
								"text": "<em>h4</em> タイトル",
								"link": null
							},
							"right": {
								"text": " タイトル",
								"link": null
							}
						},
						"attr": {
							"css": "default black",
							"narrow": "",
							"class": "default black",
							"hide": ""
						}
					}
				]
			}
		]
	}
}